documentation/djangocon-us-2024.md
documentation/learn_cdktf_docker.py
documentation/learn_helicopyter_docker.py
documentation/self2024-python-defined-infrastructure.md
helicopyter/__init__.py
helicopyter/__main__.py
helicopyter/py.typed
helicopyter-2025.20.1.dist-info/licenses/LICENSE
hooks/post_gen_project.bash
node_modules/cdk8s-cli/templates/python-app/main.py
node_modules/flatted/python/flatted.py
node_modules/flatted/python/test.py
providers/null.py
stacks/__init__.py
stacks/base.py
helicopyter-2025.20.1.dist-info/METADATA
helicopyter-2025.20.1.dist-info/WHEEL
helicopyter-2025.20.1.dist-info/top_level.txt
helicopyter-2025.20.1.dist-info/RECORD
