Metadata-Version: 2.4
Name: helicopyter
Version: 2025.20.1
Summary: Python Terraform JSON configuration generator
Project-URL: source, https://github.com/biobuddies/helicopyter
Classifier: Programming Language :: Python :: 3
Classifier: License :: OSI Approved :: Mozilla Public License 2.0 (MPL 2.0)
Classifier: Operating System :: OS Independent
Classifier: Topic :: System :: Systems Administration
Classifier: Topic :: System :: Installation/Setup
License-File: LICENSE
Requires-Dist: cdk8s
Requires-Dist: cdktf
Requires-Dist: cdktf-cdktf-provider-null
Requires-Dist: typed-argument-parser
Provides-Extra: buildrelease
Requires-Dist: build; extra == "buildrelease"
Requires-Dist: ipython; extra == "buildrelease"
Requires-Dist: twine; extra == "buildrelease"
Provides-Extra: demos
Requires-Dist: cdktf-cdktf-provider-aws; extra == "demos"
Requires-Dist: cdktf-cdktf-provider-cloudflare==11.*; extra == "demos"
Requires-Dist: cdktf-cdktf-provider-docker; extra == "demos"
Requires-Dist: cdktf-cdktf-provider-github; extra == "demos"
Provides-Extra: precommit
Requires-Dist: actionlint-py; extra == "precommit"
Requires-Dist: codespell>=2.3; extra == "precommit"
Requires-Dist: cookiecutter; extra == "precommit"
Requires-Dist: django-upgrade; extra == "precommit"
Requires-Dist: djlint; extra == "precommit"
Requires-External: hadolint-py@ git+https://github.com/AleksaC/hadolint-py.git ; extra == "precommit"
Requires-Dist: mypy; extra == "precommit"
Requires-Dist: pre-commit; extra == "precommit"
Requires-Dist: pytest; extra == "precommit"
Requires-Dist: pytest-cov; extra == "precommit"
Requires-Dist: ruff; extra == "precommit"
Requires-Dist: rust-just; extra == "precommit"
Requires-Dist: shellcheck-py; extra == "precommit"
Requires-Dist: shfmt-py; extra == "precommit"
Requires-Dist: types-setuptools; extra == "precommit"
Requires-Dist: validate-pyproject[all]; extra == "precommit"
Requires-Dist: yamllint; extra == "precommit"
Dynamic: license-file
